<?xml version="1.0" encoding="UTF-8"?>
<TED_EXPORT xmlns:xlink="http://www.w3.org/1999/xlink"
            xmlns:xsi="http://www.w3.org/2001/XMLSchema-instance"
            xmlns="ted/R2.0.9.S02/publication"
            xmlns:n2016="ted/2016/nuts"
            xsi:schemaLocation="ted/R2.0.9.S02/publication TED_EXPORT.xsd"
            VERSION="R2.0.9.S02.E01"
            DOC_ID="017616-2018"
            EDITION="2018010">
   <TECHNICAL_SECTION>
      <RECEPTION_ID>18-018521-001</RECEPTION_ID>
      <DELETION_DATE>20180201</DELETION_DATE>
      <FORM_LG_LIST>DA </FORM_LG_LIST>
      <COMMENTS>From Convertor</COMMENTS>
   </TECHNICAL_SECTION>
   <LINKS_SECTION>
      <XML_SCHEMA_DEFINITION_LINK xlink:type="simple"
                                  xlink:href="http://ted.europa.eu"
                                  xlink:title="TED WEBSITE"/>
      <OFFICIAL_FORMS_LINK xlink:type="simple" xlink:href="http://ted.europa.eu"/>
      <FORMS_LABELS_LINK xlink:type="simple" xlink:href="http://ted.europa.eu"/>
      <ORIGINAL_CPV_LINK xlink:type="simple" xlink:href="http://ted.europa.eu"/>
      <ORIGINAL_NUTS_LINK xlink:type="simple" xlink:href="http://ted.europa.eu"/>
   </LINKS_SECTION>
   <CODED_DATA_SECTION>
      <REF_OJS>
         <COLL_OJ>S</COLL_OJ>
         <NO_OJ>10</NO_OJ>
         <DATE_PUB>20180116</DATE_PUB>
      </REF_OJS>
      <NOTICE_DATA>
         <NO_DOC_OJS>2018/S 010-017616</NO_DOC_OJS>
         <URI_LIST>
            <URI_DOC LG="DA">http://ted.europa.eu/udl?uri=TED:NOTICE:017616-2018:TEXT:DA:HTML</URI_DOC>
         </URI_LIST>
         <LG_ORIG>DA</LG_ORIG>
         <ISO_COUNTRY VALUE="DK"/>
         <IA_URL_GENERAL>http://www.vest.rm.dk</IA_URL_GENERAL>
         <ORIGINAL_CPV CODE="71400000">Urban planning and landscape architectural services</ORIGINAL_CPV>
         <ORIGINAL_CPV CODE="45000000">Construction work</ORIGINAL_CPV>
         <ORIGINAL_CPV CODE="71200000">Architectural and related services</ORIGINAL_CPV>
         <ORIGINAL_CPV CODE="71300000">Engineering services</ORIGINAL_CPV>
         <n2016:PERFORMANCE_NUTS CODE="DK041">Vestjylland</n2016:PERFORMANCE_NUTS>
         <n2016:CA_CE_NUTS CODE="DK04">Midtjylland</n2016:CA_CE_NUTS>
         <REF_NOTICE>
            <NO_DOC_OJS>2017/S 245-511249</NO_DOC_OJS>
         </REF_NOTICE>
      </NOTICE_DATA>
      <CODIF_DATA>
         <DS_DATE_DISPATCH>20180112</DS_DATE_DISPATCH>
         <DT_DATE_FOR_SUBMISSION>20180119 12:00</DT_DATE_FOR_SUBMISSION>
         <AA_AUTHORITY_TYPE CODE="3">Regional or local authority</AA_AUTHORITY_TYPE>
         <TD_DOCUMENT_TYPE CODE="2">Additional information</TD_DOCUMENT_TYPE>
         <NC_CONTRACT_NATURE CODE="1">Works</NC_CONTRACT_NATURE>
         <PR_PROC CODE="B">Competitive procedure with negotiation</PR_PROC>
         <RP_REGULATION CODE="5">European Union, with participation by GPA countries</RP_REGULATION>
         <TY_TYPE_BID CODE="1">Submission for all lots</TY_TYPE_BID>
         <AC_AWARD_CRIT CODE="2">The most economic tender</AC_AWARD_CRIT>
         <MA_MAIN_ACTIVITIES CODE="H">Health</MA_MAIN_ACTIVITIES>
         <HEADING>01A14</HEADING>
         <INITIATOR>01</INITIATOR>
      </CODIF_DATA>
   </CODED_DATA_SECTION>
   <TRANSLATION_SECTION>
      <ML_TITLES>
         <ML_TI_DOC LG="BG">
            <TI_CY>Дaния</TI_CY>
            <TI_TOWN>Herning</TI_TOWN>
            <TI_TEXT>
               <P>Строителни и монтажни работи</P>
            </TI_TEXT>
         </ML_TI_DOC>
         <ML_TI_DOC LG="CS">
            <TI_CY>Dánsko</TI_CY>
            <TI_TOWN>Herning</TI_TOWN>
            <TI_TEXT>
               <P>Stavební práce</P>
            </TI_TEXT>
         </ML_TI_DOC>
         <ML_TI_DOC LG="DA">
            <TI_CY>Danmark</TI_CY>
            <TI_TOWN>Herning</TI_TOWN>
            <TI_TEXT>
               <P>Bygge- og anlægsarbejder</P>
            </TI_TEXT>
         </ML_TI_DOC>
         <ML_TI_DOC LG="DE">
            <TI_CY>Dänemark</TI_CY>
            <TI_TOWN>Herning</TI_TOWN>
            <TI_TEXT>
               <P>Bauarbeiten</P>
            </TI_TEXT>
         </ML_TI_DOC>
         <ML_TI_DOC LG="EL">
            <TI_CY>Δανία</TI_CY>
            <TI_TOWN>Herning</TI_TOWN>
            <TI_TEXT>
               <P>Κατασκευαστικές εργασίες</P>
            </TI_TEXT>
         </ML_TI_DOC>
         <ML_TI_DOC LG="EN">
            <TI_CY>Denmark</TI_CY>
            <TI_TOWN>Herning</TI_TOWN>
            <TI_TEXT>
               <P>Construction work</P>
            </TI_TEXT>
         </ML_TI_DOC>
         <ML_TI_DOC LG="ES">
            <TI_CY>Dinamarca</TI_CY>
            <TI_TOWN>Herning</TI_TOWN>
            <TI_TEXT>
               <P>Trabajos de construcción</P>
            </TI_TEXT>
         </ML_TI_DOC>
         <ML_TI_DOC LG="ET">
            <TI_CY>Taani</TI_CY>
            <TI_TOWN>Herning</TI_TOWN>
            <TI_TEXT>
               <P>Ehitustööd</P>
            </TI_TEXT>
         </ML_TI_DOC>
         <ML_TI_DOC LG="FI">
            <TI_CY>Tanska</TI_CY>
            <TI_TOWN>Herning</TI_TOWN>
            <TI_TEXT>
               <P>Rakennustyöt</P>
            </TI_TEXT>
         </ML_TI_DOC>
         <ML_TI_DOC LG="FR">
            <TI_CY>Danemark</TI_CY>
            <TI_TOWN>Herning</TI_TOWN>
            <TI_TEXT>
               <P>Travaux de construction</P>
            </TI_TEXT>
         </ML_TI_DOC>
         <ML_TI_DOC LG="GA">
            <TI_CY>Danmhairg, an</TI_CY>
            <TI_TOWN>Herning</TI_TOWN>
            <TI_TEXT>
               <P>Construction work</P>
            </TI_TEXT>
         </ML_TI_DOC>
         <ML_TI_DOC LG="HR">
            <TI_CY>Danska</TI_CY>
            <TI_TOWN>Herning</TI_TOWN>
            <TI_TEXT>
               <P>Građevinski radovi</P>
            </TI_TEXT>
         </ML_TI_DOC>
         <ML_TI_DOC LG="HU">
            <TI_CY>Dánia</TI_CY>
            <TI_TOWN>Herning</TI_TOWN>
            <TI_TEXT>
               <P>Építési munkák</P>
            </TI_TEXT>
         </ML_TI_DOC>
         <ML_TI_DOC LG="IT">
            <TI_CY>Danimarca</TI_CY>
            <TI_TOWN>Herning</TI_TOWN>
            <TI_TEXT>
               <P>Lavori di costruzione</P>
            </TI_TEXT>
         </ML_TI_DOC>
         <ML_TI_DOC LG="LT">
            <TI_CY>Danija</TI_CY>
            <TI_TOWN>Herning</TI_TOWN>
            <TI_TEXT>
               <P>Statybos darbai</P>
            </TI_TEXT>
         </ML_TI_DOC>
         <ML_TI_DOC LG="LV">
            <TI_CY>Dānija</TI_CY>
            <TI_TOWN>Herning</TI_TOWN>
            <TI_TEXT>
               <P>Celtniecības darbi</P>
            </TI_TEXT>
         </ML_TI_DOC>
         <ML_TI_DOC LG="MT">
            <TI_CY>id-Danimarka</TI_CY>
            <TI_TOWN>Herning</TI_TOWN>
            <TI_TEXT>
               <P>Xogħol tal-kostruzzjoni</P>
            </TI_TEXT>
         </ML_TI_DOC>
         <ML_TI_DOC LG="NL">
            <TI_CY>Denemarken</TI_CY>
            <TI_TOWN>Herning</TI_TOWN>
            <TI_TEXT>
               <P>Bouwwerkzaamheden</P>
            </TI_TEXT>
         </ML_TI_DOC>
         <ML_TI_DOC LG="PL">
            <TI_CY>Dania</TI_CY>
            <TI_TOWN>Herning</TI_TOWN>
            <TI_TEXT>
               <P>Roboty budowlane</P>
            </TI_TEXT>
         </ML_TI_DOC>
         <ML_TI_DOC LG="PT">
            <TI_CY>Dinamarca</TI_CY>
            <TI_TOWN>Herning</TI_TOWN>
            <TI_TEXT>
               <P>Construção</P>
            </TI_TEXT>
         </ML_TI_DOC>
         <ML_TI_DOC LG="RO">
            <TI_CY>Danemarca</TI_CY>
            <TI_TOWN>Herning</TI_TOWN>
            <TI_TEXT>
               <P>Lucrări de construcţii</P>
            </TI_TEXT>
         </ML_TI_DOC>
         <ML_TI_DOC LG="SK">
            <TI_CY>Dánsko</TI_CY>
            <TI_TOWN>Herning</TI_TOWN>
            <TI_TEXT>
               <P>Stavebné práce</P>
            </TI_TEXT>
         </ML_TI_DOC>
         <ML_TI_DOC LG="SL">
            <TI_CY>Danska</TI_CY>
            <TI_TOWN>Herning</TI_TOWN>
            <TI_TEXT>
               <P>Gradbena dela</P>
            </TI_TEXT>
         </ML_TI_DOC>
         <ML_TI_DOC LG="SV">
            <TI_CY>Danmark</TI_CY>
            <TI_TOWN>Herning</TI_TOWN>
            <TI_TEXT>
               <P>Anläggningsarbete</P>
            </TI_TEXT>
         </ML_TI_DOC>
      </ML_TITLES>
      <ML_AA_NAMES>
         <AA_NAME LG="DA">Region Midtjylland, Hospitalsenheden Vest</AA_NAME>
      </ML_AA_NAMES>
   </TRANSLATION_SECTION>
   <FORM_SECTION>
      <F14_2014 CATEGORY="ORIGINAL" FORM="F14" LG="DA">
         <CONTRACTING_BODY>
            <ADDRESS_CONTRACTING_BODY>
               <OFFICIALNAME>Region Midtjylland, Hospitalsenheden Vest</OFFICIALNAME>
               <ADDRESS>Regionshospitalet Herning, Gl. Landevej 61</ADDRESS>
               <TOWN>Herning</TOWN>
               <POSTAL_CODE>7400</POSTAL_CODE>
               <COUNTRY VALUE="DK"/>
               <CONTACT_POINT>Michael Hyllegaard</CONTACT_POINT>
               <E_MAIL>bigm@niras.dk</E_MAIL>
               <n2016:NUTS CODE="DK04"/>
               <URL_GENERAL>http://www.vest.rm.dk</URL_GENERAL>
            </ADDRESS_CONTRACTING_BODY>
         </CONTRACTING_BODY>
         <OBJECT_CONTRACT>
            <TITLE>
               <P>NIDO | danmark</P>
            </TITLE>
            <CPV_MAIN>
               <CPV_CODE CODE="45000000"/>
            </CPV_MAIN>
            <TYPE_CONTRACT CTYPE="WORKS"/>
            <SHORT_DESCR>
               <P>Udbuddet omhandler byggeriet af NIDO | danmark (NIDO), som udbydes i totalentreprise med til Region Midtjylland som bygherre. NIDO er et forsknings- og uddannelsescenter, som placeres i direkte tilknytning til Det Nye Hospital i Vest (DNV-Gødstrup). NIDO vil – når det er fuldt udbygget – indeholde laboratorier, kontorarbejdspladser, enheder til kliniske forsøg, biobank, undervisningslokaler, mødefaciliteter, aula og auditorium. NIDO forventes at udgøre et areal på ca. 3 000 - 6 000 m2. NIDO udbydes i omvendt licitation.</P>
            </SHORT_DESCR>
         </OBJECT_CONTRACT>
         <COMPLEMENTARY_INFO>
            <DATE_DISPATCH_NOTICE>2018-01-12</DATE_DISPATCH_NOTICE>
            <NOTICE_NUMBER_OJ>2017/S 245-511249</NOTICE_NUMBER_OJ>
         </COMPLEMENTARY_INFO>
         <CHANGES>
            <CHANGE PUBLICATION="YES">
               <WHERE>
                  <SECTION>II.2.4</SECTION>
               </WHERE>
               <OLD_VALUE>
                  <TEXT>
                     <P>Udbuddet omhandler byggeriet af NIDO, som udbydes i totalentreprise med Region Midtjylland som bygherre. NIDO er et forsknings- og uddannelsescenter, som placeres i direkte tilknytning til Det Nye Hospital i Vest (DNV-Gødstrup). Centeret er et selvstændigt projekt med finansiering fra Region Midtjylland og private donationer.NIDO vil – når det er fuldt udbygget – indeholde laboratorier, kontorarbejdspladser, enheder til kliniske forsøg, biobank, undervisningslokaler, mødefaciliteter, aula og auditorium.</P>
                     <P>NIDO forventes at udgøre et areal på ca. 3 000 - 6 000 m2.</P>
                     <P>Der er i juni 2016 udarbejdet et byggeprogram og i marts 2017 er der udarbejdet et skitseforslag for NIDO,som viser et væsentligt større finansieringsbehov end der er til rådighed på nuværende tidspunkt. Bygherre har derfor valgt at udbyde byggeriet i omvendt licitation, for at afdække hvor mange funktioner (i prioriteretrækkefølge), der kan etableres for den aktuelle finansiering, med mulighed for efterfølgende at etablere de resterende funktioner i den takt der er finansiering til det.</P>
                     <P>Tilbudsgiverne konkurrerer således på at tilbyde flest mulige funktioner (i prioriteret rækkefølge) i den bedste kvalitet indenfor den anlægsøkonomi, der er til rådighed på tilbudstidspunktet. De funktioner, der ikke kan rummes indenfor den anlægsøkonomi, der er til rådighed på tilbudstidspunktet, skal tilbydes som optioner, og således at tilbudsgiverne konkurrerer på prisen for disse optioner.</P>
                     <P>Bygherren søger imidlertid om yderligere økonomisk støtte til projektet (donationer). I det omfang en sådan støtte bliver tildelt inden udbuddets afslutning, vil anlægsøkonomien (og dermed den økonomi, tilbudsgiverne skal tilbyde flest mulige funktioner indenfor) blive forøget med den tildelte støtte. I det omfang, der tildeles yderligere støtte til projektet efter udbuddet, vil sådanne yderligere midler blive anvendt til at realisere (i prioriteret rækkefølge) de funktioner, der ikke kan rummes indenfor den anlægsøkonomi, der var til rådighed på tilbudstidspunktet.</P>
                  </TEXT>
               </OLD_VALUE>
               <NEW_VALUE>
                  <TEXT>
                     <P>Udbuddet omhandler byggeriet af NIDO, som udbydes i totalentreprise med Region Midtjylland som bygherre. NIDO er et forsknings- og uddannelsescenter, som placeres i direkte tilknytning til Det Nye Hospital i Vest (DNV-Gødstrup). Centeret er et selvstændigt projekt med finansiering fra Region Midtjylland og private donationer.NIDO vil – når det er fuldt udbygget – indeholde laboratorier, kontorarbejdspladser, enheder til kliniske forsøg, biobank, undervisningslokaler, mødefaciliteter, aula og auditorium.</P>
                     <P>NIDO forventes at udgøre et areal på ca. 3 000 - 6 000 m2.</P>
                     <P>Der er i juni 2016 udarbejdet et byggeprogram og i marts 2017 er der udarbejdet et skitseforslag for NIDO,som viser et væsentligt større finansieringsbehov end der er til rådighed på nuværende tidspunkt. Bygherrehar derfor valgt at udbyde byggeriet i omvendt licitation, for at afdække hvor mange funktioner (i prioriteretrækkefølge), der kan etableres for den aktuelle finansiering, med mulighed for efterfølgende at etablere de resterende funktioner i den takt der er finansiering til det.</P>
                     <P>Tilbudsgiverne konkurrerer således på at tilbyde flest mulige funktioner (i prioriteret rækkefølge) i den bedste kvalitet indenfor den anlægsøkonomi, der er til rådighed på tilbudstidspunktet. De funktioner, der ikke kan rummes indenfor den anlægsøkonomi, der er til rådighed på tilbudstidspunktet, skal tilbydes som optioner, og således at tilbudsgiverne konkurrerer på prisen for disse optioner.</P>
                     <P>Bygherren søger imidlertid om yderligere økonomisk støtte til projektet (donationer). I det omfang en sådan støtte bliver tildelt inden udbuddets afslutning, vil anlægsøkonomien (og dermed den økonomi, tilbudsgiverne skal tilbyde flest mulige funktioner indenfor) blive forøget med den tildelte støtte. I det omfang, der tildeles yderligere støtte til projektet efter udbuddet, vil sådanne yderligere midler blive anvendt til at realisere (i prioriteret rækkefølge) de funktioner, der ikke kan rummes indenfor den anlægsøkonomi, der var til rådighed på tilbudstidspunktet.</P>
                     <P>Desuden udbydes i option indretning, aptering og installationsarbejderne for arealerne til Klinisk Socialmedicin &amp; Rehabilitering (herefter KSR). Lokalerne til KSR er placeret i stueplan i det nordvestlige hjørne af DNV-Gødstrup. Der er i stueplan afsat et bruttoareal til funktionen på 471 m2, inkl. ydermure, teknikrum, trappetårn og elevatorskakt. Under KSR er der tunnel/kælder/teknikrum på 154 m2 brutto. På nuværende tidspunkt er råhuset, hvor KSR får til huse, færdigbygget og facaden er muret op og vinduer isat. KSR skal efter planen flytte ind i de nye lokaler samtidig med ibrugtagning af det øvrige hospital, det vil sige ultimo 2019/primo 2020 afhængig af den konkrete flytteplan.</P>
                  </TEXT>
               </NEW_VALUE>
            </CHANGE>
            <CHANGE PUBLICATION="YES">
               <WHERE>
                  <SECTION>III.1.2</SECTION>
               </WHERE>
               <OLD_VALUE>
                  <TEXT>
                     <P>Udvælgelseskriterier som angivet i udbudsmaterialet</P>
                  </TEXT>
               </OLD_VALUE>
               <NEW_VALUE>
                  <TEXT>
                     <P>Ansøger bedes angive følgende regnskabsoplysninger for de tre seneste disponible regnskabsår, under hensyntagen til, hvornår ansøger blev etableret eller startede sin virksomhed:</P>
                     <P>Årlig omsætning:</P>
                     <P>- Mindstekrav: Ansøgers årlige omsætning skal i hvert regnskabsår være mindst 100 mio. kr. </P>
                     <P>Egenkapital med tillæg af en eventuel ansvarlig lånekapital:</P>
                     <P>- Mindstekrav: Ansøgers egenkapital det seneste disponible regnskabsår er minimum 25 mio. kr. Soliditetsgrad:</P>
                     <P>Mindstekrav: Ansøgers soliditetsgrad det seneste disponible regnskabsår er minimum 15 %.</P>
                  </TEXT>
               </NEW_VALUE>
            </CHANGE>
            <INFO_ADD>
               <P>Der gøres opmærksom på, at der d. 12. januar 2018 er uploadet et rettelsesblad 01 med tilhørende reviderede udbudsdokumenter til udbuddet på Byggeweb.</P>
            </INFO_ADD>
         </CHANGES>
      </F14_2014>
   </FORM_SECTION>
</TED_EXPORT>
