<?xml version="1.0" encoding="UTF-8"?><TED_EXPORT xmlns:xlink="http://www.w3.org/1999/xlink" xmlns:xsi="http://www.w3.org/2001/XMLSchema-instance" xmlns="ted/R2.0.8.S03/publication" xmlns:n2016="ted/2016/nuts" xsi:schemaLocation="ted/R2.0.8.S03/publication TED_EXPORT.xsd" DOC_ID="045075-2018" EDITION="2018021"><TECHNICAL_SECTION><RECEPTION_ID>18-043227-001</RECEPTION_ID><DELETION_DATE>20180506</DELETION_DATE><FORM_LG_LIST>HR </FORM_LG_LIST><COMMENTS>From Convertor</COMMENTS></TECHNICAL_SECTION><LINKS_SECTION><XML_SCHEMA_DEFINITION_LINK xlink:type="simple" xlink:href="http://ted.europa.eu" xlink:title="TED WEBSITE"/><OFFICIAL_FORMS_LINK xlink:type="simple" xlink:href="http://ted.europa.eu"/><FORMS_LABELS_LINK xlink:type="simple" xlink:href="http://ted.europa.eu"/><ORIGINAL_CPV_LINK xlink:type="simple " xlink:href="http://ted.europa.eu"/><ORIGINAL_NUTS_LINK xlink:type="simple" xlink:href="http://ted.europa.eu"/></LINKS_SECTION><CODED_DATA_SECTION><REF_OJS><COLL_OJ>S</COLL_OJ><NO_OJ>21</NO_OJ><DATE_PUB>20180131</DATE_PUB></REF_OJS><NOTICE_DATA><NO_DOC_OJS>2018/S 021-045075</NO_DOC_OJS><URI_LIST><URI_DOC LG="HR">http://ted.europa.eu/udl?uri=TED:NOTICE:045075-2018:TEXT:HR:HTML</URI_DOC></URI_LIST><LG_ORIG>HR</LG_ORIG><ISO_COUNTRY VALUE="HR"/><IA_URL_GENERAL/><IA_URL_ETENDERING>https://eojn.nn.hr/SPIN/application/ipn/DocumentManagement/DokumentPodaciFrm.aspx?OznakaDokumenta=2018%2fS+003-0002040</IA_URL_ETENDERING><ORIGINAL_CPV CODE="30192000">Office supplies</ORIGINAL_CPV><n2016:PERFORMANCE_NUTS CODE="HR041">Grad Zagreb</n2016:PERFORMANCE_NUTS><VALUES_LIST><VALUES TYPE="CONTRACT"><SINGLE_VALUE><VALUE CURRENCY="HRK">4 893 777,00</VALUE></SINGLE_VALUE></VALUES><VALUES TYPE="CONTRACT"><SINGLE_VALUE><VALUE CURRENCY="HRK">10 070 540,00</VALUE></SINGLE_VALUE></VALUES><VALUES TYPE="CONTRACT"><SINGLE_VALUE><VALUE CURRENCY="HRK">8 499 615,00</VALUE></SINGLE_VALUE></VALUES></VALUES_LIST><REF_NOTICE><NO_DOC_OJS>2016/S 146-264647</NO_DOC_OJS></REF_NOTICE></NOTICE_DATA><CODIF_DATA><DS_DATE_DISPATCH>20180126</DS_DATE_DISPATCH><AA_AUTHORITY_TYPE CODE="3">Regional or local authority</AA_AUTHORITY_TYPE><TD_DOCUMENT_TYPE CODE="7">Contract award notice</TD_DOCUMENT_TYPE><NC_CONTRACT_NATURE CODE="2">Supplies</NC_CONTRACT_NATURE><PR_PROC CODE="1">Open procedure</PR_PROC><RP_REGULATION CODE="4">European Union</RP_REGULATION><TY_TYPE_BID CODE="9">Not applicable</TY_TYPE_BID><AC_AWARD_CRIT CODE="1">Lowest price</AC_AWARD_CRIT><MA_MAIN_ACTIVITIES CODE="S">General public services</MA_MAIN_ACTIVITIES><HEADING>01203</HEADING><DIRECTIVE VALUE="2004/18/EC"/></CODIF_DATA></CODED_DATA_SECTION><TRANSLATION_SECTION><ML_TITLES><ML_TI_DOC LG="BG"><TI_CY>Хърватска</TI_CY><TI_TOWN>Загреб</TI_TOWN><TI_TEXT>Принадлежности за офиса</TI_TEXT></ML_TI_DOC><ML_TI_DOC LG="CS"><TI_CY>Chorvatsko</TI_CY><TI_TOWN>Záhřeb</TI_TOWN><TI_TEXT>Kancelářské potřeby</TI_TEXT></ML_TI_DOC><ML_TI_DOC LG="DA"><TI_CY>Kroatien</TI_CY><TI_TOWN>Zagreb</TI_TOWN><TI_TEXT>Kontortilbehør</TI_TEXT></ML_TI_DOC><ML_TI_DOC LG="DE"><TI_CY>Kroatien</TI_CY><TI_TOWN>Zagreb</TI_TOWN><TI_TEXT>Bürobedarf</TI_TEXT></ML_TI_DOC><ML_TI_DOC LG="EL"><TI_CY>Κροατία</TI_CY><TI_TOWN>Ζάγκρεμπ</TI_TOWN><TI_TEXT>Προμήθειες ειδών γραφείου</TI_TEXT></ML_TI_DOC><ML_TI_DOC LG="EN"><TI_CY>Croatia</TI_CY><TI_TOWN>Zagreb</TI_TOWN><TI_TEXT>Office supplies</TI_TEXT></ML_TI_DOC><ML_TI_DOC LG="ES"><TI_CY>Croacia</TI_CY><TI_TOWN>Zagreb</TI_TOWN><TI_TEXT>Artículos de oficina</TI_TEXT></ML_TI_DOC><ML_TI_DOC LG="ET"><TI_CY>Horvaatia</TI_CY><TI_TOWN>Zagreb</TI_TOWN><TI_TEXT>Kantseleitarbed</TI_TEXT></ML_TI_DOC><ML_TI_DOC LG="FI"><TI_CY>Kroatia</TI_CY><TI_TOWN>Zagreb</TI_TOWN><TI_TEXT>Toimistotarvikkeet</TI_TEXT></ML_TI_DOC><ML_TI_DOC LG="FR"><TI_CY>Croatie</TI_CY><TI_TOWN>Zagreb</TI_TOWN><TI_TEXT>Fournitures de bureau</TI_TEXT></ML_TI_DOC><ML_TI_DOC LG="GA"><TI_CY>Chróit, an</TI_CY><TI_TOWN>Ságrab</TI_TOWN><TI_TEXT>Office supplies</TI_TEXT></ML_TI_DOC><ML_TI_DOC LG="HR"><TI_CY>Hrvatska</TI_CY><TI_TOWN>Zagreb</TI_TOWN><TI_TEXT>Uredske potrepštine</TI_TEXT></ML_TI_DOC><ML_TI_DOC LG="HU"><TI_CY>Horvátország</TI_CY><TI_TOWN>Zágráb</TI_TOWN><TI_TEXT>Irodai kellékek</TI_TEXT></ML_TI_DOC><ML_TI_DOC LG="IT"><TI_CY>Croazia</TI_CY><TI_TOWN>Zagabria</TI_TOWN><TI_TEXT>Materiale per ufficio</TI_TEXT></ML_TI_DOC><ML_TI_DOC LG="LT"><TI_CY>Kroatija</TI_CY><TI_TOWN>Zagrebas</TI_TOWN><TI_TEXT>Biuro reikmenys</TI_TEXT></ML_TI_DOC><ML_TI_DOC LG="LV"><TI_CY>Horvātija</TI_CY><TI_TOWN>Zagreba</TI_TOWN><TI_TEXT>Biroja piederumi</TI_TEXT></ML_TI_DOC><ML_TI_DOC LG="MT"><TI_CY>il-Kroazja</TI_CY><TI_TOWN>Żagreb</TI_TOWN><TI_TEXT>Fornimenti ta' l-uffiċini</TI_TEXT></ML_TI_DOC><ML_TI_DOC LG="NL"><TI_CY>Kroatië</TI_CY><TI_TOWN>Zagreb</TI_TOWN><TI_TEXT>Kantoorbenodigdheden</TI_TEXT></ML_TI_DOC><ML_TI_DOC LG="PL"><TI_CY>Chorwacja</TI_CY><TI_TOWN>Zagrzeb</TI_TOWN><TI_TEXT>Wyroby biurowe</TI_TEXT></ML_TI_DOC><ML_TI_DOC LG="PT"><TI_CY>Croácia</TI_CY><TI_TOWN>Zagrebe</TI_TOWN><TI_TEXT>Material de escritório</TI_TEXT></ML_TI_DOC><ML_TI_DOC LG="RO"><TI_CY>Croaţia</TI_CY><TI_TOWN>Zagreb</TI_TOWN><TI_TEXT>Accesorii de birou</TI_TEXT></ML_TI_DOC><ML_TI_DOC LG="SK"><TI_CY>Chorvátsko</TI_CY><TI_TOWN>Záhreb</TI_TOWN><TI_TEXT>Kancelárske potreby</TI_TEXT></ML_TI_DOC><ML_TI_DOC LG="SL"><TI_CY>Hrvaška</TI_CY><TI_TOWN>Zagreb</TI_TOWN><TI_TEXT>Pisarniške potrebščine</TI_TEXT></ML_TI_DOC><ML_TI_DOC LG="SV"><TI_CY>Kroatien</TI_CY><TI_TOWN>Zagreb</TI_TOWN><TI_TEXT>Kontorsmateriel</TI_TEXT></ML_TI_DOC></ML_TITLES><ML_AA_NAMES><AA_NAME LG="HR">Grad Zagreb</AA_NAME></ML_AA_NAMES></TRANSLATION_SECTION><FORM_SECTION><CONTRACT_AWARD CATEGORY="ORIGINAL" FORM="3" LG="HR" VERSION="R2.0.8.S03.E01"><FD_CONTRACT_AWARD CTYPE="SUPPLIES"><CONTRACTING_AUTHORITY_INFORMATION_CONTRACT_AWARD><NAME_ADDRESSES_CONTACT_CONTRACT_AWARD><CA_CE_CONCESSIONAIRE_PROFILE><ORGANISATION><OFFICIALNAME>Grad Zagreb</OFFICIALNAME><NATIONALID>61817894937</NATIONALID></ORGANISATION><ADDRESS>Avenija Dubrovnik 15</ADDRESS><TOWN>Zagreb</TOWN><POSTAL_CODE>10020</POSTAL_CODE><COUNTRY VALUE="HR"/><CONTACT_POINT>Središnje tijelo za javnu nabavu</CONTACT_POINT><ATTENTION>javna.nabava@zagreb.hr</ATTENTION></CA_CE_CONCESSIONAIRE_PROFILE><INTERNET_ADDRESSES_CONTRACT_AWARD><URL_INFORMATION>https://eojn.nn.hr/SPIN/application/ipn/DocumentManagement/DokumentPodaciFrm.aspx?OznakaDokumenta=2018%2fS+003-0002040</URL_INFORMATION><URL_PARTICIPATE>https://eojn.nn.hr/Oglasnik</URL_PARTICIPATE></INTERNET_ADDRESSES_CONTRACT_AWARD></NAME_ADDRESSES_CONTACT_CONTRACT_AWARD><TYPE_AND_ACTIVITIES_AND_PURCHASING_ON_BEHALF><TYPE_AND_ACTIVITIES><TYPE_OF_CONTRACTING_AUTHORITY VALUE="REGIONAL_AUTHORITY"/><TYPE_OF_ACTIVITY VALUE="GENERAL_PUBLIC_SERVICES"/></TYPE_AND_ACTIVITIES><PURCHASING_ON_BEHALF><PURCHASING_ON_BEHALF_YES><CONTACT_DATA_OTHER_BEHALF_CONTRACTING_AUTORITHY><ORGANISATION><OFFICIALNAME>Zagrebački Holding d.o.o., Ulica grada Vukovara 41, Zagreb, OIB: 85584865987, tel.: 385 (01) 6420 510, fax.: 385 (01) 6429 072, internetska adresa: www.zgh.hr, e-mail: nabava@zgh.hrVODOOPSKRBA I ODVODNJA d.o.o., Folnegovićeva 1, Zagreb 10 000, OIB: 83416546499, tel.: +385 (01) 6163 000, internetska adresa: www.vio.hr.GRADSKO STAMBENO KOMUNALNO GOSPODARSTVO d.o.o., Savska cesta 1, Zagreb, OIB: 03744272526, internetska adresa: www.gskg.hrGRADSKA PLINARA ZAGREB – OPSKRBA d.o.o., Radnička cesta 1, 10000 Zagreb, OIB: 74364571096, tel.: +385 (0)1 6302-333, e-mail: opskrba@gpz-opskrba.hr., web adresa: www.gpz-opskrba.hrGRADSKA PLINARA ZAGREB d.o.o., Radnička cesta 1, Zagreb, OIB: 20985255037, tel.: 385 (01) 6437 777, fax.: 385 (01) 4698 600, internetska adresa: www.plinara-zagreb.hr, e-mail: info-gpz@plinara-zagreb.hriAGM d.o.o., Mihanovićeva 28, Zagreb, OIB: 37620818018, tel: 4856 307, fax: 4856 316, e-mail: agm@agm.hr</OFFICIALNAME><NATIONALID>.</NATIONALID></ORGANISATION><COUNTRY VALUE="HR"/></CONTACT_DATA_OTHER_BEHALF_CONTRACTING_AUTORITHY></PURCHASING_ON_BEHALF_YES></PURCHASING_ON_BEHALF></TYPE_AND_ACTIVITIES_AND_PURCHASING_ON_BEHALF></CONTRACTING_AUTHORITY_INFORMATION_CONTRACT_AWARD><OBJECT_CONTRACT_INFORMATION_CONTRACT_AWARD_NOTICE><DESCRIPTION_AWARD_NOTICE_INFORMATION><TITLE_CONTRACT><P>TONERI I TINTE</P></TITLE_CONTRACT><TYPE_CONTRACT_LOCATION_W_PUB><TYPE_CONTRACT VALUE="SUPPLIES"/><TYPE_SUPPLIES_CONTRACT VALUE="PURCHASE"/></TYPE_CONTRACT_LOCATION_W_PUB><LOCATION_NUTS><LOCATION><P>Mjesto izvršenja predmeta nabave je grad Zagreb.</P><P>Duljina trajanja sklopljenih ugovora izdanih na temelju Okvirnog sporazuma: utvrdit će se prilikom slanja ponovljenog poziva za dostavu ponude (upita za ponudu), a ovisiti će o stvarnim potrebama Naručitelja.</P><P>Dinamika isporuke: sukcesivno tijekom trajanja ugovora, prema potrebama Naručitelja.</P><P>Pojedinačni rok isporuke: ne smije biti duži od 2 (dva) dana.</P><P>Rok početka isporuke: Nakon zaprimljene narudžbenice.</P></LOCATION><n2016:NUTS CODE="HR041"/></LOCATION_NUTS><NOTICE_INVOLVES_DESC><CONCLUSION_FRAMEWORK_AGREEMENT/></NOTICE_INVOLVES_DESC><SHORT_CONTRACT_DESCRIPTION><P>Predmet nabave je: TONERI I TINTE.</P></SHORT_CONTRACT_DESCRIPTION><CPV><CPV_MAIN><CPV_CODE CODE="30192000"/></CPV_MAIN></CPV><CONTRACT_COVERED_GPA VALUE="NO"/></DESCRIPTION_AWARD_NOTICE_INFORMATION></OBJECT_CONTRACT_INFORMATION_CONTRACT_AWARD_NOTICE><PROCEDURE_DEFINITION_CONTRACT_AWARD_NOTICE><TYPE_OF_PROCEDURE_DEF><PT_OPEN/></TYPE_OF_PROCEDURE_DEF><AWARD_CRITERIA_CONTRACT_AWARD_NOTICE_INFORMATION><AWARD_CRITERIA_DETAIL_F03><LOWEST_PRICE/></AWARD_CRITERIA_DETAIL_F03><F03_IS_ELECTRONIC_AUCTION_USABLE VALUE="NO"/></AWARD_CRITERIA_CONTRACT_AWARD_NOTICE_INFORMATION><ADMINISTRATIVE_INFORMATION_CONTRACT_AWARD><FILE_REFERENCE_NUMBER><P>2016-1</P></FILE_REFERENCE_NUMBER><PREVIOUS_PUBLICATION_INFORMATION_NOTICE_F3><PREVIOUS_PUBLICATION_EXISTS_F3><CNT_NOTICE_INFORMATION><CNT_NOTICE_INFORMATION_S CHOICE="CONTRACT_NOTICE"/><NOTICE_NUMBER_OJ>2016/S 146-264647</NOTICE_NUMBER_OJ><DATE_OJ><DAY>30</DAY><MONTH>07</MONTH><YEAR>2016</YEAR></DATE_OJ></CNT_NOTICE_INFORMATION><NO_OTHER_PREVIOUS_PUBLICATION/></PREVIOUS_PUBLICATION_EXISTS_F3></PREVIOUS_PUBLICATION_INFORMATION_NOTICE_F3></ADMINISTRATIVE_INFORMATION_CONTRACT_AWARD></PROCEDURE_DEFINITION_CONTRACT_AWARD_NOTICE><AWARD_OF_CONTRACT ITEM="1"><CONTRACT_NUMBER>18/2018</CONTRACT_NUMBER><LOT_NUMBER>1</LOT_NUMBER><CONTRACT_TITLE><P>TONERI I TINTE</P></CONTRACT_TITLE><CONTRACT_AWARD_DATE><DAY>05</DAY><MONTH>01</MONTH><YEAR>2018</YEAR></CONTRACT_AWARD_DATE><OFFERS_RECEIVED_NUMBER>5</OFFERS_RECEIVED_NUMBER><OFFERS_RECEIVED_NUMBER_MEANING>5</OFFERS_RECEIVED_NUMBER_MEANING><ECONOMIC_OPERATOR_NAME_ADDRESS><CONTACT_DATA_WITHOUT_RESPONSIBLE_NAME><ORGANISATION><OFFICIALNAME>Tip-Zagreb d.o.o.</OFFICIALNAME><NATIONALID>36198195227</NATIONALID></ORGANISATION><ADDRESS>Vinogradska 34</ADDRESS><TOWN>Sveta Nedelja</TOWN><POSTAL_CODE>10431</POSTAL_CODE><COUNTRY VALUE="HR"/></CONTACT_DATA_WITHOUT_RESPONSIBLE_NAME></ECONOMIC_OPERATOR_NAME_ADDRESS><CONTRACT_VALUE_INFORMATION><INITIAL_ESTIMATED_TOTAL_VALUE_CONTRACT CURRENCY="HRK"><VALUE_COST FMTVAL="8100000.00">8 100 000,00</VALUE_COST><EXCLUDING_VAT/></INITIAL_ESTIMATED_TOTAL_VALUE_CONTRACT><COSTS_RANGE_AND_CURRENCY_WITH_VAT_RATE CURRENCY="HRK"><VALUE_COST FMTVAL="4893777.00">4 893 777,00</VALUE_COST></COSTS_RANGE_AND_CURRENCY_WITH_VAT_RATE></CONTRACT_VALUE_INFORMATION><MORE_INFORMATION_TO_SUB_CONTRACTED><NO_CONTRACT_LIKELY_SUB_CONTRACTED/></MORE_INFORMATION_TO_SUB_CONTRACTED></AWARD_OF_CONTRACT><AWARD_OF_CONTRACT ITEM="2"><CONTRACT_NUMBER>18/2018</CONTRACT_NUMBER><LOT_NUMBER>1</LOT_NUMBER><CONTRACT_TITLE><P>TONERI I TINTE</P></CONTRACT_TITLE><CONTRACT_AWARD_DATE><DAY>05</DAY><MONTH>01</MONTH><YEAR>2018</YEAR></CONTRACT_AWARD_DATE><OFFERS_RECEIVED_NUMBER>5</OFFERS_RECEIVED_NUMBER><OFFERS_RECEIVED_NUMBER_MEANING>5</OFFERS_RECEIVED_NUMBER_MEANING><ECONOMIC_OPERATOR_NAME_ADDRESS><CONTACT_DATA_WITHOUT_RESPONSIBLE_NAME><ORGANISATION><OFFICIALNAME>EBC Sistemi d.o.o.</OFFICIALNAME><NATIONALID>34583734418</NATIONALID></ORGANISATION><ADDRESS>Zvonimira Rogoza 20</ADDRESS><TOWN>Zagreb</TOWN><POSTAL_CODE>10000</POSTAL_CODE><COUNTRY VALUE="HR"/><E_MAILS><E_MAIL>ebc@ebc.hr</E_MAIL></E_MAILS><PHONE>+385 16043356</PHONE><FAX>+385 16043355</FAX></CONTACT_DATA_WITHOUT_RESPONSIBLE_NAME></ECONOMIC_OPERATOR_NAME_ADDRESS><CONTRACT_VALUE_INFORMATION><INITIAL_ESTIMATED_TOTAL_VALUE_CONTRACT CURRENCY="HRK"><VALUE_COST FMTVAL="8100000.00">8 100 000,00</VALUE_COST><EXCLUDING_VAT/></INITIAL_ESTIMATED_TOTAL_VALUE_CONTRACT><COSTS_RANGE_AND_CURRENCY_WITH_VAT_RATE CURRENCY="HRK"><VALUE_COST FMTVAL="10070540.00">10 070 540,00</VALUE_COST></COSTS_RANGE_AND_CURRENCY_WITH_VAT_RATE></CONTRACT_VALUE_INFORMATION><MORE_INFORMATION_TO_SUB_CONTRACTED><NO_CONTRACT_LIKELY_SUB_CONTRACTED/></MORE_INFORMATION_TO_SUB_CONTRACTED></AWARD_OF_CONTRACT><AWARD_OF_CONTRACT ITEM="3"><CONTRACT_NUMBER>18/2018</CONTRACT_NUMBER><LOT_NUMBER>1</LOT_NUMBER><CONTRACT_TITLE><P>TONERI I TINTE</P></CONTRACT_TITLE><CONTRACT_AWARD_DATE><DAY>05</DAY><MONTH>01</MONTH><YEAR>2018</YEAR></CONTRACT_AWARD_DATE><OFFERS_RECEIVED_NUMBER>5</OFFERS_RECEIVED_NUMBER><OFFERS_RECEIVED_NUMBER_MEANING>5</OFFERS_RECEIVED_NUMBER_MEANING><ECONOMIC_OPERATOR_NAME_ADDRESS><CONTACT_DATA_WITHOUT_RESPONSIBLE_NAME><ORGANISATION><OFFICIALNAME>Zajednica ponuditelja: Zvibor d.o.o.; Lacus d.o.o.; Makromikro Grupa d.o.o.; Novi Ured d.o.o.</OFFICIALNAME><NATIONALID>03454358063</NATIONALID></ORGANISATION><ADDRESS>Zavrtnica 36</ADDRESS><TOWN>Zagreb</TOWN><POSTAL_CODE>10000</POSTAL_CODE><COUNTRY VALUE="HR"/><E_MAILS><E_MAIL>zvibor@zvibor.hr</E_MAIL></E_MAILS><PHONE>+385 16323020</PHONE><FAX>+385 16323080</FAX></CONTACT_DATA_WITHOUT_RESPONSIBLE_NAME></ECONOMIC_OPERATOR_NAME_ADDRESS><CONTRACT_VALUE_INFORMATION><INITIAL_ESTIMATED_TOTAL_VALUE_CONTRACT CURRENCY="HRK"><VALUE_COST FMTVAL="8100000.00">8 100 000,00</VALUE_COST><EXCLUDING_VAT/></INITIAL_ESTIMATED_TOTAL_VALUE_CONTRACT><COSTS_RANGE_AND_CURRENCY_WITH_VAT_RATE CURRENCY="HRK"><VALUE_COST FMTVAL="8499615.00">8 499 615,00</VALUE_COST></COSTS_RANGE_AND_CURRENCY_WITH_VAT_RATE></CONTRACT_VALUE_INFORMATION><MORE_INFORMATION_TO_SUB_CONTRACTED><NO_CONTRACT_LIKELY_SUB_CONTRACTED/></MORE_INFORMATION_TO_SUB_CONTRACTED></AWARD_OF_CONTRACT><COMPLEMENTARY_INFORMATION_CONTRACT_AWARD><RELATES_TO_EU_PROJECT_NO/><PROCEDURES_FOR_APPEAL><APPEAL_PROCEDURE_BODY_RESPONSIBLE><CONTACT_DATA_WITHOUT_RESPONSIBLE_NAME><ORGANISATION><OFFICIALNAME>Državna komisija za kontrolu postupaka javne nabave</OFFICIALNAME><NATIONALID>95857869241</NATIONALID></ORGANISATION><ADDRESS>Koturaška cesta 43/IV</ADDRESS><TOWN>Zagreb</TOWN><POSTAL_CODE>10000</POSTAL_CODE><COUNTRY VALUE="HR"/><E_MAILS><E_MAIL>dkom@dkom.hr</E_MAIL></E_MAILS><PHONE>+385 14559930</PHONE><URL>www.dkom.hr</URL><FAX>+385 14559933</FAX></CONTACT_DATA_WITHOUT_RESPONSIBLE_NAME></APPEAL_PROCEDURE_BODY_RESPONSIBLE></PROCEDURES_FOR_APPEAL><NOTICE_DISPATCH_DATE><DAY>26</DAY><MONTH>01</MONTH><YEAR>2018</YEAR></NOTICE_DISPATCH_DATE></COMPLEMENTARY_INFORMATION_CONTRACT_AWARD></FD_CONTRACT_AWARD></CONTRACT_AWARD></FORM_SECTION></TED_EXPORT>