<?xml version="1.0" encoding="UTF-8"?>
<TED_EXPORT xmlns:xlink="http://www.w3.org/1999/xlink"
            xmlns:xsi="http://www.w3.org/2001/XMLSchema-instance"
            xmlns="ted/R2.0.9.S02/publication"
            xmlns:n2016="ted/2016/nuts"
            xsi:schemaLocation="ted/R2.0.9.S02/publication TED_EXPORT.xsd"
            VERSION="R2.0.9.S02.E01"
            DOC_ID="006518-2018"
            EDITION="2018005">
   <TECHNICAL_SECTION>
      <RECEPTION_ID>18-005589-001</RECEPTION_ID>
      <DELETION_DATE>20180123</DELETION_DATE>
      <FORM_LG_LIST>HU </FORM_LG_LIST>
      <COMMENTS>From Convertor</COMMENTS>
   </TECHNICAL_SECTION>
   <LINKS_SECTION>
      <XML_SCHEMA_DEFINITION_LINK xlink:type="simple"
                                  xlink:href="http://ted.europa.eu"
                                  xlink:title="TED WEBSITE"/>
      <OFFICIAL_FORMS_LINK xlink:type="simple" xlink:href="http://ted.europa.eu"/>
      <FORMS_LABELS_LINK xlink:type="simple" xlink:href="http://ted.europa.eu"/>
      <ORIGINAL_CPV_LINK xlink:type="simple" xlink:href="http://ted.europa.eu"/>
      <ORIGINAL_NUTS_LINK xlink:type="simple" xlink:href="http://ted.europa.eu"/>
   </LINKS_SECTION>
   <CODED_DATA_SECTION>
      <REF_OJS>
         <COLL_OJ>S</COLL_OJ>
         <NO_OJ>5</NO_OJ>
         <DATE_PUB>20180109</DATE_PUB>
      </REF_OJS>
      <NOTICE_DATA>
         <NO_DOC_OJS>2018/S 005-006518</NO_DOC_OJS>
         <URI_LIST>
            <URI_DOC LG="HU">http://ted.europa.eu/udl?uri=TED:NOTICE:006518-2018:TEXT:HU:HTML</URI_DOC>
         </URI_LIST>
         <LG_ORIG>HU</LG_ORIG>
         <ISO_COUNTRY VALUE="HU"/>
         <IA_URL_GENERAL>http://www.neak.gov.hu</IA_URL_GENERAL>
         <IA_URL_ETENDERING>http://www.neak.gov.hu/felso_menu/rolunk/kozerdeku_adatok/kozbeszerzesi_informaciok/kozbeszerzesi_eljarasok/2017_unios/Teteles_elsz_ala_eso_rituximab</IA_URL_ETENDERING>
         <ORIGINAL_CPV CODE="33690000">Various medicinal products</ORIGINAL_CPV>
         <n2016:PERFORMANCE_NUTS CODE="HU1">KÖZÉP-MAGYARORSZÁG</n2016:PERFORMANCE_NUTS>
         <n2016:PERFORMANCE_NUTS CODE="HU2">DUNÁNTÚL</n2016:PERFORMANCE_NUTS>
         <n2016:PERFORMANCE_NUTS CODE="HU3">ALFÖLD ÉS ÉSZAK</n2016:PERFORMANCE_NUTS>
         <n2016:CA_CE_NUTS CODE="HU110">Budapest</n2016:CA_CE_NUTS>
      </NOTICE_DATA>
      <CODIF_DATA>
         <DS_DATE_DISPATCH>20180105</DS_DATE_DISPATCH>
         <DT_DATE_FOR_SUBMISSION>20180122 10:00</DT_DATE_FOR_SUBMISSION>
         <AA_AUTHORITY_TYPE CODE="1">Ministry or any other national or federal authority</AA_AUTHORITY_TYPE>
         <TD_DOCUMENT_TYPE CODE="3">Contract notice</TD_DOCUMENT_TYPE>
         <NC_CONTRACT_NATURE CODE="2">Supplies</NC_CONTRACT_NATURE>
         <PR_PROC CODE="B">Competitive procedure with negotiation</PR_PROC>
         <RP_REGULATION CODE="5">European Union, with participation by GPA countries</RP_REGULATION>
         <TY_TYPE_BID CODE="1">Submission for all lots</TY_TYPE_BID>
         <AC_AWARD_CRIT CODE="1">Lowest price</AC_AWARD_CRIT>
         <MA_MAIN_ACTIVITIES CODE="H">Health</MA_MAIN_ACTIVITIES>
         <HEADING>01B02</HEADING>
         <INITIATOR>01</INITIATOR>
         <DIRECTIVE VALUE="2014/24/EU"/>
      </CODIF_DATA>
   </CODED_DATA_SECTION>
   <TRANSLATION_SECTION>
      <ML_TITLES>
         <ML_TI_DOC LG="BG">
            <TI_CY>Унгapия</TI_CY>
            <TI_TOWN>Будапеща</TI_TOWN>
            <TI_TEXT>
               <P>Разни медикаменти</P>
            </TI_TEXT>
         </ML_TI_DOC>
         <ML_TI_DOC LG="CS">
            <TI_CY>Maďarsko</TI_CY>
            <TI_TOWN>Budapešť</TI_TOWN>
            <TI_TEXT>
               <P>Různé léčivé přípravky</P>
            </TI_TEXT>
         </ML_TI_DOC>
         <ML_TI_DOC LG="DA">
            <TI_CY>Ungarn</TI_CY>
            <TI_TOWN>Budapest</TI_TOWN>
            <TI_TEXT>
               <P>Diverse lægemidler</P>
            </TI_TEXT>
         </ML_TI_DOC>
         <ML_TI_DOC LG="DE">
            <TI_CY>Ungarn</TI_CY>
            <TI_TOWN>Budapest</TI_TOWN>
            <TI_TEXT>
               <P>Varia</P>
            </TI_TEXT>
         </ML_TI_DOC>
         <ML_TI_DOC LG="EL">
            <TI_CY>Ουγγαρία</TI_CY>
            <TI_TOWN>Βουδαπέστη</TI_TOWN>
            <TI_TEXT>
               <P>Διάφορα φάρμακα</P>
            </TI_TEXT>
         </ML_TI_DOC>
         <ML_TI_DOC LG="EN">
            <TI_CY>Hungary</TI_CY>
            <TI_TOWN>Budapest</TI_TOWN>
            <TI_TEXT>
               <P>Various medicinal products</P>
            </TI_TEXT>
         </ML_TI_DOC>
         <ML_TI_DOC LG="ES">
            <TI_CY>Hungría</TI_CY>
            <TI_TOWN>Budapest</TI_TOWN>
            <TI_TEXT>
               <P>Medicamentos diversos</P>
            </TI_TEXT>
         </ML_TI_DOC>
         <ML_TI_DOC LG="ET">
            <TI_CY>Ungari</TI_CY>
            <TI_TOWN>Budapest</TI_TOWN>
            <TI_TEXT>
               <P>Mitmesugused ravimid</P>
            </TI_TEXT>
         </ML_TI_DOC>
         <ML_TI_DOC LG="FI">
            <TI_CY>Unkari</TI_CY>
            <TI_TOWN>Budapest</TI_TOWN>
            <TI_TEXT>
               <P>Muut lääkkeet</P>
            </TI_TEXT>
         </ML_TI_DOC>
         <ML_TI_DOC LG="FR">
            <TI_CY>Hongrie</TI_CY>
            <TI_TOWN>Budapest</TI_TOWN>
            <TI_TEXT>
               <P>Médicaments divers</P>
            </TI_TEXT>
         </ML_TI_DOC>
         <ML_TI_DOC LG="GA">
            <TI_CY>Ungáir, an</TI_CY>
            <TI_TOWN>Búdaipéist</TI_TOWN>
            <TI_TEXT>
               <P>Various medicinal products</P>
            </TI_TEXT>
         </ML_TI_DOC>
         <ML_TI_DOC LG="HR">
            <TI_CY>Mađarska</TI_CY>
            <TI_TOWN>Budimpešta</TI_TOWN>
            <TI_TEXT>
               <P>Razni lijekovi</P>
            </TI_TEXT>
         </ML_TI_DOC>
         <ML_TI_DOC LG="HU">
            <TI_CY>Magyarország</TI_CY>
            <TI_TOWN>Budapest</TI_TOWN>
            <TI_TEXT>
               <P>Különböző gyógyszerek</P>
            </TI_TEXT>
         </ML_TI_DOC>
         <ML_TI_DOC LG="IT">
            <TI_CY>Ungheria</TI_CY>
            <TI_TOWN>Budapest</TI_TOWN>
            <TI_TEXT>
               <P>Medicinali vari</P>
            </TI_TEXT>
         </ML_TI_DOC>
         <ML_TI_DOC LG="LT">
            <TI_CY>Vengrija</TI_CY>
            <TI_TOWN>Budapeštas</TI_TOWN>
            <TI_TEXT>
               <P>Kiti vaistai</P>
            </TI_TEXT>
         </ML_TI_DOC>
         <ML_TI_DOC LG="LV">
            <TI_CY>Ungārija</TI_CY>
            <TI_TOWN>Budapešta</TI_TOWN>
            <TI_TEXT>
               <P>Dažādas zāles</P>
            </TI_TEXT>
         </ML_TI_DOC>
         <ML_TI_DOC LG="MT">
            <TI_CY>l-Ungerija</TI_CY>
            <TI_TOWN>Budapest</TI_TOWN>
            <TI_TEXT>
               <P>Prodotti mediċinali varji</P>
            </TI_TEXT>
         </ML_TI_DOC>
         <ML_TI_DOC LG="NL">
            <TI_CY>Hongarije</TI_CY>
            <TI_TOWN>Boedapest</TI_TOWN>
            <TI_TEXT>
               <P>Diverse geneesmiddelen</P>
            </TI_TEXT>
         </ML_TI_DOC>
         <ML_TI_DOC LG="PL">
            <TI_CY>Węgry</TI_CY>
            <TI_TOWN>Budapeszt</TI_TOWN>
            <TI_TEXT>
               <P>Różne produkty lecznicze</P>
            </TI_TEXT>
         </ML_TI_DOC>
         <ML_TI_DOC LG="PT">
            <TI_CY>Hungria</TI_CY>
            <TI_TOWN>Budapeste</TI_TOWN>
            <TI_TEXT>
               <P>Medicamentos vários</P>
            </TI_TEXT>
         </ML_TI_DOC>
         <ML_TI_DOC LG="RO">
            <TI_CY>Ungaria</TI_CY>
            <TI_TOWN>Budapesta</TI_TOWN>
            <TI_TEXT>
               <P>Diverse medicamente</P>
            </TI_TEXT>
         </ML_TI_DOC>
         <ML_TI_DOC LG="SK">
            <TI_CY>Maďarsko</TI_CY>
            <TI_TOWN>Budapešť</TI_TOWN>
            <TI_TEXT>
               <P>Rôzne liečivá</P>
            </TI_TEXT>
         </ML_TI_DOC>
         <ML_TI_DOC LG="SL">
            <TI_CY>Madžarska</TI_CY>
            <TI_TOWN>Budimpešta</TI_TOWN>
            <TI_TEXT>
               <P>Različna zdravila</P>
            </TI_TEXT>
         </ML_TI_DOC>
         <ML_TI_DOC LG="SV">
            <TI_CY>Ungern</TI_CY>
            <TI_TOWN>Budapest</TI_TOWN>
            <TI_TEXT>
               <P>Varia</P>
            </TI_TEXT>
         </ML_TI_DOC>
      </ML_TITLES>
      <ML_AA_NAMES>
         <AA_NAME LG="HU">Nemzeti Egészségbiztosítási Alapkezelő</AA_NAME>
      </ML_AA_NAMES>
   </TRANSLATION_SECTION>
   <FORM_SECTION>
      <F02_2014 CATEGORY="ORIGINAL" FORM="F02" LG="HU">
         <CONTRACTING_BODY>
            <ADDRESS_CONTRACTING_BODY>
               <OFFICIALNAME>Nemzeti Egészségbiztosítási Alapkezelő</OFFICIALNAME>
               <NATIONALID>AK16195</NATIONALID>
               <ADDRESS>Váci út 73/A.</ADDRESS>
               <TOWN>Budapest</TOWN>
               <POSTAL_CODE>1139</POSTAL_CODE>
               <COUNTRY VALUE="HU"/>
               <CONTACT_POINT>Beleznai Gábor</CONTACT_POINT>
               <PHONE>+361 3502001</PHONE>
               <E_MAIL>kozbeszerzes@neak.gov.hu</E_MAIL>
               <FAX>+36 12982463</FAX>
               <n2016:NUTS CODE="HU110"/>
               <URL_GENERAL>http://www.neak.gov.hu</URL_GENERAL>
               <URL_BUYER>http://www.neak.gov.hu</URL_BUYER>
            </ADDRESS_CONTRACTING_BODY>
            <CENTRAL_PURCHASING/>
            <DOCUMENT_FULL/>
            <URL_DOCUMENT>http://www.neak.gov.hu/felso_menu/rolunk/kozerdeku_adatok/kozbeszerzesi_informaciok/kozbeszerzesi_eljarasok/2017_unios/Teteles_elsz_ala_eso_rituximab</URL_DOCUMENT>
            <ADDRESS_FURTHER_INFO_IDEM/>
            <ADDRESS_PARTICIPATION_IDEM/>
            <CA_TYPE VALUE="MINISTRY"/>
            <CA_ACTIVITY VALUE="HEALTH"/>
         </CONTRACTING_BODY>
         <OBJECT_CONTRACT>
            <TITLE>
               <P>Tételes elszámolás alá eső rituximab, valamint immunglobulin hatóanyagot tartalmazó, természetben biztosítandó gyógyszerek 2018–2019. finanszírozási évre történő beszerzése 7 részben</P>
            </TITLE>
            <REFERENCE_NUMBER>F082/6/2017</REFERENCE_NUMBER>
            <CPV_MAIN>
               <CPV_CODE CODE="33690000"/>
            </CPV_MAIN>
            <TYPE_CONTRACT CTYPE="SUPPLIES"/>
            <SHORT_DESCR>
               <P>1. rész Rituximab hatóanyag beszerzése NM rendelet 1/A. számú melléklet 7/b1, 7/b2, 7/b3 pontja szerinti valamely indikáció(k)ban történő kezelésre összesen 16 200 000 mg mennyiségben</P>
               <P>2. rész Szubkután immunglobulin, glicin stabilizálószerrel összesen 65 640 300 mg mennyiségben</P>
               <P>3. rész Intravénás immunglobulin, liquid, maltóz stabilizálószerrel 5 %-os koncentrációjú összesen 38 654 000 mg mennyiségben</P>
               <P>4. rész Intravénás immunglobulin, liquid, maltóz stabilizálószerrel 10 %-os koncentrációjú összesen 22 560 000 mg mennyiségben</P>
               <P>5. rész Intravénás immunglobulin, liquid, cukormentes, glicin stabilizálószerrel összesen 53 000 000 mg mennyiségben</P>
               <P>6. rész Szubkután immunglobulin, prolin stabilizálószerrel összesen 22 108 000 mg mennyiségben</P>
               <P>7. rész Intravénás immunglobulin, liquid, prolin stabilizálószerrel összesen 34 540 000 mg mennyiségben</P>
            </SHORT_DESCR>
            <LOT_DIVISION>
               <LOT_ALL/>
            </LOT_DIVISION>
            <OBJECT_DESCR ITEM="1">
               <TITLE>
                  <P>Tételes elsz. alá eső rituximab, valamint immunglobulin hatóanyagot tartalmazó, term-ben bizt. gyógyszerek 2018–2019. fin. évre történő beszerzése 7 részben</P>
               </TITLE>
               <LOT_NO>1.</LOT_NO>
               <CPV_ADDITIONAL>
                  <CPV_CODE CODE="33690000"/>
               </CPV_ADDITIONAL>
               <n2016:NUTS CODE="HU1"/>
               <n2016:NUTS CODE="HU2"/>
               <n2016:NUTS CODE="HU3"/>
               <MAIN_SITE>
                  <P>Magyarország teljes területe, az NM rendelet 1/A számú melléklete szerint.</P>
               </MAIN_SITE>
               <SHORT_DESCR>
                  <P>Rituximab hatóanyag beszerzése NM rendelet 1/A. számú melléklet 7/b1, 7/b2, 7/b3 pontja szerinti valamely indikáció(k)ban történő kezelésre összesen 16 200 000 mg mennyiségben.</P>
                  <P>A gyógyszerek és orvostechnikai eszközök közbeszerzésének sajátos szabályairól szóló 16/2012. (II. 16.) Korm. rendelet (a továbbiakban: 16/2012. Korm. rendelet) 6. § (3) bekezdése alapján a Kbt. 76. § (6) bekezdés a) pontja szerinti, a legalacsonyabb ár egyedüli értékelési szempontját kívánjuk alkalmazni.</P>
                  <P>Ajánlatkérő nem írja elő rabatt adásának kötelezettségét, de Ajánlattevőnek lehetősége van annak megajánlására. Az eljárás során egyedüli értékelési szempontként az ár került meghatározásra. A kiírt mennyiségen felüli, vagy esetlegesen üzleti titokként kezelt rabatt nem kerül értékelésre. Felhívjuk a gazdasági szereplők figyelmét, hogy a felhívás II.2.7. pontját ajánlatkérő a kitölthetőség technikai lehetőségeire tekintettel határozta meg, de a dokumentációban és a keretmegállapodás tervezetben ismertetettek szerint a keretmegállapodás annak mindkét fél általi aláírásának napján lép hatályba és határozott, 2019. október 31-ig tartó aktív, 2020. február 29-ig tartó passzív időszakra jön létre. A keretmegállapodás időbeli hatályának kezdete, a közbeszerzési eljárás eredményes lezárását követően, annak mindkét fél által történt aláírásának a napja.</P>
               </SHORT_DESCR>
               <AC_PRICE/>
               <DURATION TYPE="MONTH">20</DURATION>
               <RENEWAL/>
               <RENEWAL_DESCR>
                  <P>Mindenben változatlan szerződéses feltételekkel legfeljebb egy alkalommal még 12 hónap aktív időszakra.</P>
               </RENEWAL_DESCR>
               <NO_ACCEPTED_VARIANTS/>
               <NO_OPTIONS/>
               <NO_EU_PROGR_RELATED/>
               <INFO_ADD>
                  <P>II.2.6) pontban a becsült érték nem szerepel, azt Ajánlatkérő nem kívánja megadni!</P>
                  <P>Ajánlatkérő nem alkalmazza a 75.§ (2) bekezdés e) pontban foglaltakat.</P>
               </INFO_ADD>
            </OBJECT_DESCR>
            <OBJECT_DESCR ITEM="2">
               <TITLE>
                  <P>Tételes elszámolás alá eső rituximab, valamint immunglobulin hatóanyagot tartalmazó, természetben biztosítandó gyógyszerek 2018–2019. finanszírozási évre történő beszerzése 7 részben</P>
               </TITLE>
               <LOT_NO>2.</LOT_NO>
               <CPV_ADDITIONAL>
                  <CPV_CODE CODE="33690000"/>
               </CPV_ADDITIONAL>
               <n2016:NUTS CODE="HU2"/>
               <n2016:NUTS CODE="HU3"/>
               <n2016:NUTS CODE="HU1"/>
               <MAIN_SITE>
                  <P>Magyarország teljes területe, az NM rendelet 1/A számú melléklete szerint.</P>
               </MAIN_SITE>
               <SHORT_DESCR>
                  <P>Szubkután immunglobulin, glicin stabilizálószerrel összesen 65 640 300 mg mennyiségben.</P>
                  <P>A gyógyszerek és orvostechnikai eszközök közbeszerzésének sajátos szabályairól szóló 16/2012. (II. 16.) Korm. rendelet (a továbbiakban: 16/2012. Korm. rendelet) 6. § (3) bekezdése alapján a Kbt. 76. § (6) bekezdés a) pontja szerinti, a legalacsonyabb ár egyedüli értékelési szempontját kívánjuk alkalmazni.</P>
                  <P>Ajánlatkérő nem írja elő rabatt adásának kötelezettségét, de Ajánlattevőnek lehetősége van annak megajánlására. Az eljárás során egyedüli értékelési szempontként az ár került meghatározásra. A kiírt mennyiségen felüli, vagy esetlegesen üzleti titokként kezelt rabatt nem kerül értékelésre. Felhívjuk a gazdasági szereplők figyelmét, hogy a felhívás II.2.7. pontját ajánlatkérő a kitölthetőség technikai lehetőségeire tekintettel határozta meg, de a dokumentációban és a keretmegállapodás tervezetben ismertetettek szerint a keretmegállapodás annak mindkét fél általi aláírásának napján lép hatályba és határozott, 2019. október 31-ig tartó aktív, 2020. február 29-ig tartó passzív időszakra jön létre. A keretmegállapodás időbeli hatályának kezdete, a közbeszerzési eljárás eredményes lezárását követően, annak mindkét fél által történt aláírásának a napja.</P>
               </SHORT_DESCR>
               <AC_PRICE/>
               <DURATION TYPE="MONTH">20</DURATION>
               <RENEWAL/>
               <RENEWAL_DESCR>
                  <P>Mindenben változatlan szerződéses feltételekkel legfeljebb egy alkalommal még 12 hónap aktív időszakra.</P>
               </RENEWAL_DESCR>
               <NO_ACCEPTED_VARIANTS/>
               <NO_OPTIONS/>
               <NO_EU_PROGR_RELATED/>
               <INFO_ADD>
                  <P>II.2.6) pontban a becsült érték nem szerepel, azt Ajánlatkérő nem kívánja megadni!</P>
                  <P>Ajánlatkérő nem alkalmazza a 75.§ (2) bekezdés e) pontban foglaltakat.</P>
               </INFO_ADD>
            </OBJECT_DESCR>
            <OBJECT_DESCR ITEM="3">
               <TITLE>
                  <P>Tételes elszámolás alá eső rituximab, valamint immunglobulin hatóanyagot tartalmazó, természetben biztosítandó gyógyszerek 2018-2019. finanszírozási évre történő beszerzése 7 részben</P>
               </TITLE>
               <LOT_NO>3.</LOT_NO>
               <CPV_ADDITIONAL>
                  <CPV_CODE CODE="33690000"/>
               </CPV_ADDITIONAL>
               <n2016:NUTS CODE="HU1"/>
               <n2016:NUTS CODE="HU2"/>
               <n2016:NUTS CODE="HU3"/>
               <MAIN_SITE>
                  <P>Magyarország teljes területe, az NM rendelet 1/A számú melléklete szerint.</P>
               </MAIN_SITE>
               <SHORT_DESCR>
                  <P>Intravénás immunglobulin, liquid, maltóz stabilizálószerrel 5 %-os koncentrációjú összesen 38 654 000 mg mennyiségben.</P>
                  <P>A gyógyszerek és orvostechnikai eszközök közbeszerzésének sajátos szabályairól szóló 16/2012. (II. 16.) Korm. rendelet (a továbbiakban: 16/2012. Korm. rendelet) 6. § (3) bekezdése alapján a Kbt. 76. § (6) bekezdés a) pontja szerinti, a legalacsonyabb ár egyedüli értékelési szempontját kívánjuk alkalmazni.</P>
                  <P>Ajánlatkérő nem írja elő rabatt adásának kötelezettségét, de Ajánlattevőnek lehetősége van annak megajánlására. Az eljárás során egyedüli értékelési szempontként az ár került meghatározásra. A kiírt mennyiségen felüli, vagy esetlegesen üzleti titokként kezelt rabatt nem kerül értékelésre. Felhívjuk a gazdasági szereplők figyelmét, hogy a felhívás II.2.7. pontját ajánlatkérő a kitölthetőség technikai lehetőségeire tekintettel határozta meg, de a dokumentációban és a keretmegállapodás tervezetben ismertetettek szerint a keretmegállapodás annak mindkét fél általi aláírásának napján lép hatályba és határozott, 2019. október 31-ig tartó aktív, 2020. február 29-ig tartó passzív időszakra jön létre. A keretmegállapodás időbeli hatályának kezdete, a közbeszerzési eljárás eredményes lezárását követően, annak mindkét fél által történt aláírásának a napja.</P>
               </SHORT_DESCR>
               <AC_PRICE/>
               <DURATION TYPE="MONTH">20</DURATION>
               <RENEWAL/>
               <RENEWAL_DESCR>
                  <P>Mindenben változatlan szerződéses feltételekkel legfeljebb egy alkalommal még 12 hónap aktív időszakra.</P>
               </RENEWAL_DESCR>
               <NO_ACCEPTED_VARIANTS/>
               <NO_OPTIONS/>
               <NO_EU_PROGR_RELATED/>
               <INFO_ADD>
                  <P>II.2.6) pontban a becsült érték nem szerepel, azt Ajánlatkérő nem kívánja megadni!</P>
                  <P>Ajánlatkérő nem alkalmazza a 75.§ (2) bekezdés e) pontban foglaltakat.</P>
               </INFO_ADD>
            </OBJECT_DESCR>
            <OBJECT_DESCR ITEM="4">
               <TITLE>
                  <P>Tételes elsz. alá eső rituximab, valamint immunglobulin hatóanyagot tartalmazó, term-ben bizt. gyógyszerek 2018–2019. fin. évre történő beszerzése 7 részben</P>
               </TITLE>
               <LOT_NO>4.</LOT_NO>
               <CPV_ADDITIONAL>
                  <CPV_CODE CODE="33690000"/>
               </CPV_ADDITIONAL>
               <n2016:NUTS CODE="HU1"/>
               <n2016:NUTS CODE="HU2"/>
               <n2016:NUTS CODE="HU3"/>
               <MAIN_SITE>
                  <P>Magyarország teljes területe, az NM rendelet 1/A számú melléklete szerint.</P>
               </MAIN_SITE>
               <SHORT_DESCR>
                  <P>Intravénás immunglobulin, liquid, maltóz stabilizálószerrel 10 %-os koncentrációjú összesen 22 560 000 mg mennyiségben.</P>
                  <P>A gyógyszerek és orvostechnikai eszközök közbeszerzésének sajátos szabályairól szóló 16/2012. (II. 16.) Korm. rendelet (a továbbiakban: 16/2012. Korm. rendelet) 6. § (3) bekezdése alapján a Kbt. 76. § (6) bekezdés a) pontja szerinti, a legalacsonyabb ár egyedüli értékelési szempontját kívánjuk alkalmazni.</P>
                  <P>Ajánlatkérő nem írja elő rabatt adásának kötelezettségét, de Ajánlattevőnek lehetősége van annak megajánlására. Az eljárás során egyedüli értékelési szempontként az ár került meghatározásra. A kiírt mennyiségen felüli, vagy esetlegesen üzleti titokként kezelt rabatt nem kerül értékelésre. Felhívjuk a gazdasági szereplők figyelmét, hogy a felhívás II.2.7. pontját ajánlatkérő a kitölthetőség technikai lehetőségeire tekintettel határozta meg, de a dokumentációban és a keretmegállapodás tervezetben ismertetettek szerint a keretmegállapodás annak mindkét fél általi aláírásának napján lép hatályba és határozott, 2019. október 31-ig tartó aktív, 2020. február 29-ig tartó passzív időszakra jön létre. A keretmegállapodás időbeli hatályának kezdete, a közbeszerzési eljárás eredményes lezárását követően, annak mindkét fél által történt aláírásának a napja.</P>
               </SHORT_DESCR>
               <AC_PRICE/>
               <DURATION TYPE="MONTH">20</DURATION>
               <RENEWAL/>
               <RENEWAL_DESCR>
                  <P>Mindenben változatlan szerződéses feltételekkel legfeljebb egy alkalommal még 12 hónap aktív időszakra.</P>
               </RENEWAL_DESCR>
               <NO_ACCEPTED_VARIANTS/>
               <NO_OPTIONS/>
               <NO_EU_PROGR_RELATED/>
               <INFO_ADD>
                  <P>II.2.6) pontban a becsült érték nem szerepel, azt Ajánlatkérő nem kívánja megadni!</P>
                  <P>Ajánlatkérő nem alkalmazza a 75.§ (2) bekezdés e) pontban foglaltakat.</P>
               </INFO_ADD>
            </OBJECT_DESCR>
            <OBJECT_DESCR ITEM="5">
               <TITLE>
                  <P>Tételes elszámolás alá eső rituximab, valamint immunglobulin hatóanyagot tartalmazó, természetben biztosítandó gyógyszerek 2018–2019. finanszírozási évre történő beszerzése 7 részben</P>
               </TITLE>
               <LOT_NO>5.</LOT_NO>
               <CPV_ADDITIONAL>
                  <CPV_CODE CODE="33690000"/>
               </CPV_ADDITIONAL>
               <n2016:NUTS CODE="HU1"/>
               <n2016:NUTS CODE="HU2"/>
               <n2016:NUTS CODE="HU3"/>
               <MAIN_SITE>
                  <P>Magyarország teljes területe, az NM rendelet 1/A számú melléklete szerint.</P>
               </MAIN_SITE>
               <SHORT_DESCR>
                  <P>Intravénás immunglobulin, liquid, cukormentes, glicin stabilizálószerrel összesen 53 000 000 mg mennyiségben.</P>
                  <P>A gyógyszerek és orvostechnikai eszközök közbeszerzésének sajátos szabályairól szóló 16/2012. (II. 16.) Korm. rendelet (a továbbiakban: 16/2012. Korm. rendelet) 6. § (3) bekezdése alapján a Kbt. 76. § (6) bekezdés a) pontja szerinti, a legalacsonyabb ár egyedüli értékelési szempontját kívánjuk alkalmazni.</P>
                  <P>Ajánlatkérő nem írja elő rabatt adásának kötelezettségét, de Ajánlattevőnek lehetősége van annak megajánlására. Az eljárás során egyedüli értékelési szempontként az ár került meghatározásra. A kiírt mennyiségen felüli, vagy esetlegesen üzleti titokként kezelt rabatt nem kerül értékelésre. Felhívjuk a gazdasági szereplők figyelmét, hogy a felhívás II.2.7. pontját ajánlatkérő a kitölthetőség technikai lehetőségeire tekintettel határozta meg, de a dokumentációban és a keretmegállapodás tervezetben ismertetettek szerint a keretmegállapodás annak mindkét fél általi aláírásának napján lép hatályba és határozott, 2019. október 31-ig tartó aktív, 2020. február 29-ig tartó passzív időszakra jön létre. A keretmegállapodás időbeli hatályának kezdete, a közbeszerzési eljárás eredményes lezárását követően, annak mindkét fél által történt aláírásának a napja.</P>
               </SHORT_DESCR>
               <AC_PRICE/>
               <DURATION TYPE="MONTH">20</DURATION>
               <RENEWAL/>
               <RENEWAL_DESCR>
                  <P>Mindenben változatlan szerződéses feltételekkel legfeljebb egy alkalommal még 12 hónap aktív időszakra.</P>
               </RENEWAL_DESCR>
               <NO_ACCEPTED_VARIANTS/>
               <NO_OPTIONS/>
               <NO_EU_PROGR_RELATED/>
               <INFO_ADD>
                  <P>II.2.6) pontban a becsült érték nem szerepel, azt Ajánlatkérő nem kívánja megadni!</P>
                  <P>Ajánlatkérő nem alkalmazza a 75.§ (2) bekezdés e) pontban foglaltakat.</P>
               </INFO_ADD>
            </OBJECT_DESCR>
            <OBJECT_DESCR ITEM="6">
               <TITLE>
                  <P>Tételes elszámolás alá eső rituximab, valamint immunglobulin hatóanyagot tartalmazó, természetben biztosítandó gyógyszerek 2018–2019. finanszírozási évre történő beszerzése 7 részben</P>
               </TITLE>
               <LOT_NO>6.</LOT_NO>
               <CPV_ADDITIONAL>
                  <CPV_CODE CODE="33690000"/>
               </CPV_ADDITIONAL>
               <n2016:NUTS CODE="HU1"/>
               <n2016:NUTS CODE="HU2"/>
               <n2016:NUTS CODE="HU3"/>
               <MAIN_SITE>
                  <P>Magyarország teljes területe, az NM rendelet 1/A számú melléklete szerint.</P>
               </MAIN_SITE>
               <SHORT_DESCR>
                  <P>Szubkután immunglobulin, prolin stabilizálószerrel összesen 22 108 000 mg mennyiségben.</P>
                  <P>A gyógyszerek és orvostechnikai eszközök közbeszerzésének sajátos szabályairól szóló 16/2012. (II. 16.) Korm. rendelet (a továbbiakban: 16/2012. Korm. rendelet) 6. § (3) bekezdése alapján a Kbt. 76. § (6) bekezdés a) pontja szerinti, a legalacsonyabb ár egyedüli értékelési szempontját kívánjuk alkalmazni.</P>
                  <P>Ajánlatkérő nem írja elő rabatt adásának kötelezettségét, de Ajánlattevőnek lehetősége van annak megajánlására. Az eljárás során egyedüli értékelési szempontként az ár került meghatározásra. A kiírt mennyiségen felüli, vagy esetlegesen üzleti titokként kezelt rabatt nem kerül értékelésre. Felhívjuk a gazdasági szereplők figyelmét, hogy a felhívás II.2.7. pontját ajánlatkérő a kitölthetőség technikai lehetőségeire tekintettel határozta meg, de a dokumentációban és a keretmegállapodás tervezetben ismertetettek szerint a keretmegállapodás annak mindkét fél általi aláírásának napján lép hatályba és határozott, 2019. október 31-ig tartó aktív, 2020. február 29-ig tartó passzív időszakra jön létre. A keretmegállapodás időbeli hatályának kezdete, a közbeszerzési eljárás eredményes lezárását követően, annak mindkét fél által történt aláírásának a napja.</P>
               </SHORT_DESCR>
               <AC_PRICE/>
               <DURATION TYPE="MONTH">20</DURATION>
               <RENEWAL/>
               <RENEWAL_DESCR>
                  <P>Mindenben változatlan szerződéses feltételekkel legfeljebb egy alkalommal még 12 hónap aktív időszakra.</P>
               </RENEWAL_DESCR>
               <NO_ACCEPTED_VARIANTS/>
               <NO_OPTIONS/>
               <NO_EU_PROGR_RELATED/>
               <INFO_ADD>
                  <P>II.2.6) pontban a becsült érték nem szerepel, azt Ajánlatkérő nem kívánja megadni!</P>
                  <P>Ajánlatkérő nem alkalmazza a 75.§ (2) bekezdés e) pontban foglaltakat.</P>
               </INFO_ADD>
            </OBJECT_DESCR>
            <OBJECT_DESCR ITEM="7">
               <TITLE>
                  <P>Tételes elszámolás alá eső rituximab, valamint immunglobulin hatóanyagot tartalmazó, természetben biztosítandó gyógyszerek 2018–2019. finanszírozási évre történő beszerzése 7 részben</P>
               </TITLE>
               <LOT_NO>7.</LOT_NO>
               <CPV_ADDITIONAL>
                  <CPV_CODE CODE="33690000"/>
               </CPV_ADDITIONAL>
               <n2016:NUTS CODE="HU1"/>
               <n2016:NUTS CODE="HU2"/>
               <n2016:NUTS CODE="HU3"/>
               <MAIN_SITE>
                  <P>Magyarország teljes területe, az NM rendelet 1/A számú melléklete szerint.</P>
               </MAIN_SITE>
               <SHORT_DESCR>
                  <P>Intravénás immunglobulin, liquid, prolin stabilizálószerrel összesen 34 540 000 mg mennyiségben.</P>
                  <P>A gyógyszerek és orvostechnikai eszközök közbeszerzésének sajátos szabályairól szóló 16/2012. (II. 16.) Korm. rendelet (a továbbiakban: 16/2012. Korm. rendelet) 6. § (3) bekezdése alapján a Kbt. 76. § (6) bekezdés a) pontja szerinti, a legalacsonyabb ár egyedüli értékelési szempontját kívánjuk alkalmazni.</P>
                  <P>Ajánlatkérő nem írja elő rabatt adásának kötelezettségét, de Ajánlattevőnek lehetősége van annak megajánlására. Az eljárás során egyedüli értékelési szempontként az ár került meghatározásra. A kiírt mennyiségen felüli, vagy esetlegesen üzleti titokként kezelt rabatt nem kerül értékelésre. Felhívjuk a gazdasági szereplők figyelmét, hogy a felhívás II.2.7. pontját ajánlatkérő a kitölthetőség technikai lehetőségeire tekintettel határozta meg, de a dokumentációban és a keretmegállapodás tervezetben ismertetettek szerint a keretmegállapodás annak mindkét fél általi aláírásának napján lép hatályba és határozott, 2019. október 31-ig tartó aktív, 2020. február 29-ig tartó passzív időszakra jön létre. A keretmegállapodás időbeli hatályának kezdete, a közbeszerzési eljárás eredményes lezárását követően, annak mindkét fél által történt aláírásának a napja.</P>
               </SHORT_DESCR>
               <AC_PRICE/>
               <DURATION TYPE="MONTH">20</DURATION>
               <RENEWAL/>
               <RENEWAL_DESCR>
                  <P>Mindenben változatlan szerződéses feltételekkel legfeljebb egy alkalommal még 12 hónap aktív időszakra.</P>
               </RENEWAL_DESCR>
               <NO_ACCEPTED_VARIANTS/>
               <NO_OPTIONS/>
               <NO_EU_PROGR_RELATED/>
               <INFO_ADD>
                  <P>II.2.6) pontban a becsült érték nem szerepel, azt Ajánlatkérő nem kívánja megadni!</P>
                  <P>Ajánlatkérő nem alkalmazza a 75.§ (2) bekezdés e) pontban foglaltakat.</P>
               </INFO_ADD>
            </OBJECT_DESCR>
         </OBJECT_CONTRACT>
         <LEFTI>
            <SUITABILITY>
               <P>III.1.1) Az eljárásban nem lehet Részvételre jelentkező (közös részvételre jelentkező), alvállalkozó, és nem vehet részt az alkalmasság igazolásában olyan gazdasági szereplő, aki a Kbt. 62. § (1)-(2) bekezdésében meghatározott kizáró okok hatálya alá tartozik.</P>
               <P>A kizáró okok igazolásának módja és folyamata:</P>
               <P>A kizáró okok igazolásának módja tekintetében irányadóak: a Kbt. 67. § (1)-(3) bekezdése, a 321/2015. (X.30.) Korm. rendelet 1. §-a és 3. §-a valamint a 4. §-a.</P>
               <P>A kizáró okok fenn nem állását a 321/2015. (X. 30.) Kr. 8. §, 10. §, és 12-16. §-aiban meghatározottak szerint kell igazolni - figyelemmel a Kbt. 69. § (4) bekezdésére és 84. § (3) bekezdésére.</P>
               <P>A Kbt. 62. § (1) bekezdés k) pont kb) pontja tekintetében az igazolás módja: a Kr. 8. § i) pont ib) alpontjában, valamint a 10. § g) pont gb) alpontjában foglaltak szerint.</P>
               <P>Részvételre jelentkezőnek (közös részvételre jelentkezőnek) nyilatkoznia kell továbbá a Kbt. 67. § (4) bekezdése alapján, hogy a szerződés teljesítéséhez nem vesz igénybe a Kbt. 62. § (1)-(2) bekezdés szerinti kizáró okok hatálya alá eső alvállalkozót.</P>
               <P>A jelen közbeszerzési eljárásra tekintettel, a gazdasági szereplő által tett nyilatkozatok dátuma nem lehet korábbi keltezésű a Részvételi felhívás feladásának dátumánál. Az alkalmasság, a kizáró okok körében beadott (hatóságtól, intézménytől, vagy más szervezetektől származó) igazolások, illetve egyéb, nem a jelen eljárásra tekintettel született, de a jelentkezéshez szükséges igazolások keltezése lehet régebbi, mint a fenti dátum.</P>
               <P>Egyéb feltételek:</P>
               <P>A Kbt. 74. § (1) bekezdése értelmében: Az ajánlatkérőnek ki kell zárnia az eljárásból azt a részvételre jelentkezőt, alvállalkozót vagy az alkalmasság igazolásában részt vevő szervezetet, aki a kizáró okok [62. §] hatálya alá tartozik; illetőleg akinek a részéről a kizáró ok az eljárás során következett be; figyelemmel a Kbt. 64. §-ában foglaltakra.</P>
               <P>Ajánlatkérő a Kbt.73.§(4)-(5) alapján előírja, hogy az eljárás ajánlattételi szakaszában az ajánlattevő tájékozódjon a környezetvédelmi, szociális és munkajogi követelményekről, amelyeknek a teljesítés helyén és a szerződés teljesítése során meg kell felelni.</P>
               <P>Ajánlatkérő az ajánlattételi szakaszban Kbt. 69. § (11) alapján hatósági nyilvántartásban ellenőrzi, hogy a megajánlott készítmény szerepel-e a Magyarországon forgalomba hozatalra engedélyezett gyógyszerekről vezetett nyilvántartásban, Részvételre jelentkező szerepel-e a gyógyszer nagykereskedőkről vezetett nyilvántartásban. Ha nem Részvételre jelentkező a forgalomba hozatali engedély jogosultja, a jogosulttól származó, forgalmazási jogosultságról szóló nyilatkozat, vagy meghatalmazás benyújtása szükséges! Kbt. 73. § (1) e) alapján érvénytelen az ajánlat, ha nem felel meg a fent előírtaknak.</P>
            </SUITABILITY>
            <TECHNICAL_PROFESSIONAL_INFO>
               <P>A kiválasztási szempontok felsorolása és rövid ismertetése: M1. Egyaránt mind a hét részre vonatkozóan érvényes feltétel: A Kbt. 65. § (1) b) pontja alapján Részvételre jelentkező (közös részvételre jelentkező) a Kr. 1. § (1) bek., az 5.§ (1) bek., a 6. § és a 7. §, valamint a 21. §. (1) a) pontja és a 22. § (1)-(2) bek. alapján ismertesse az eljárást megindító felhívás feladásától visszafelé számított három évben (36 hónapban) befejezett legjelentősebb, gyógyszer szállításainak/adásvételének teljesítéseit, legalább a következő adatok megadásával: a teljesítés ideje (a teljesítés kezdő- és befejező időpontjának – év/hó/nap – megadásával), a szerződést kötő másik fél, a szállítás tárgya, mennyisége, továbbá nyilatkozni kell arról, hogy a teljesítés az előírásoknak és a szerződésnek megfelelően történt-e.</P>
               <P>Ajánlatkérő az eljárást megindító felhívás feladásától visszafelé számított három év (36 hónap) alatt befejezett, de legfeljebb hat éven (72 hónapon) belül megkezdett szállításokat veszi figyelembe. A referenciaigazolás, nyilatkozat kötelező tartalmi eleme a teljesítés kezdő és befejező időpontja is.</P>
               <P>Ajánlatkérő lehetővé teszi az előírt referenciakövetelmény több szerződésből történő teljesítését.</P>
               <P>A bemutatott referencia több részre is bemutatható - egy referencia több részteljesítésben is igazolhatja részvételre jelentkező alkalmasságát.</P>
               <P>A műszaki, illetve szakmai alkalmasság esetén a kapacitásra támaszkodás igazolására a Kbt. 65. § (6)-(7) bekezdései alapján kerülhet sor. Az előírt alkalmassági követelményeknek a közös részvételre jelentkezők együttesen is megfelelhetnek. Az alkalmassági követelményeknek a részvételre jelentkezők bármely más szervezet vagy személy kapacitására támaszkodva is megfelelhetnek, a közöttük fennálló kapcsolat jogi jellegétől függetlenül. Ebben az esetben meg kell jelölni a Részvételre jelentkező jelentkezésében ezt a szervezetet, és az eljárást megindító felhívás vonatkozó pontjának megjelölésével, azon alkalmassági követelményt vagy követelményeket, amelynek igazolása érdekében a Részvételre jelentkező (közös részvételre jelentkező) ezen szervezet erőforrására vagy arra is támaszkodik. Csatolni kell a Részvételre jelentkező jelentkezésében a kapacitásait rendelkezésre bocsátó szervezet olyan szerződéses vagy előszerződésben vállalt kötelezettségvállalását tartalmazó okiratot, amely alátámasztja, hogy a szerződés teljesítéséhez szükséges erőforrások rendelkezésre állnak majd a szerződés teljesítésének időtartama alatt.</P>
               <P>Alkalmasság igazolása során figyelemmel kell lenni a Kbt. 69. § (4) bekezdésére és 84. § (3) bekezdésére.</P>
               <P>A dokumentumok a Kbt. 47. § (2) bekezdése szerint egyszerű másolati formában benyújthatók.</P>
               <P>Ajánlatkérő a Kr. 2. § (5) bekezdésében foglaltak alapján tájékoztatja Részvételre jelentkezőket (közös részvételre jelentkezőt), hogy az egységes európai közbeszerzési dokumentum formanyomtatványában megjelölten az alkalmassági követelmények előzetes igazolására elfogadja az érintett gazdasági szereplő egyszerű nyilatkozatát (IV. rész: „alfa” pontjában), azaz az alkalmassági követelményekre vonatkozó részt nem kell a formanyomtatványban kitölteni.</P>
            </TECHNICAL_PROFESSIONAL_INFO>
            <TECHNICAL_PROFESSIONAL_MIN_LEVEL>
               <P>M1. Egyaránt mind a hét részre vonatkozóan érvényes feltétel: Alkalmatlan részvételre jelentkező (vagy közös részvételre jelentkező), amennyiben (együttesen) a jelen felhívás feladását megelőző három év (36 hónap) alatt befejezett, de legfeljebb hat éven (72 hónapon) belül megkezdett időszakban, összességében nem rendelkezik legalább egy, bármely gyógyszerrel – az adott gyógyszer alkalmazási előírásában foglaltaknak megfelelően – történő, legalább 50 beteg egy éves kezelésre elegendő gyógyszermennyiség szállítására/adásvételére vonatkozó teljesített szerződéssel.</P>
            </TECHNICAL_PROFESSIONAL_MIN_LEVEL>
            <PERFORMANCE_CONDITIONS>
               <P>Fő finanszírozási, fizetési feltételek: a Kbt. 135. § (1), (5)-(6), az Art. 36/A. §, a Ptk. 6:130. § és a Ptk. 6:155. § szerint. 2011. évi CXCVI. tv. 3. §.</P>
               <P>Keretmegállapodást (továbbiakban: KM) biztosító mellékkötelezettségek: késedelmes, hibás teljesítés, illetve nem teljesítés esetére kötbérfizetési kötelezettség, a Ptk. 6:186. § (1)-ben foglaltakra figyelemmel. Késedelmi/hibás teljesítési kötbér maximum elérése: azonnali hatályú felmondás, meghiúsulási kötbér érvényesítése. Ptk. 6:187. § (1)-(2).</P>
               <P>Felmondás, elállás: Kbt. 143. § (1)-(3); Kbt. 104.§(7). A közbeszerzési dokumentumokban részletezettek szerint. A részletes fizetési feltételeket, a KM-t biztosító mellékkötelezettségeket és a közvetlen megrendelés teljesítésének részletszabályait a KM tervezete tartalmazza.</P>
            </PERFORMANCE_CONDITIONS>
         </LEFTI>
         <PROCEDURE>
            <PT_COMPETITIVE_NEGOTIATION/>
            <ACCELERATED_PROC>
               <P>A gyógyszerek és orvostechnikai eszközök közbeszerzésének sajátos szabályairól szóló 16/2012. (II. 16.) Korm. rendelet (a továbbiakban: 16/2012. Korm. rendelet) 14. § (1) bekezdése alapján a Kbt. 85. § (2) bekezdés c) pontja szerinti körülménynek kell tekinteni a gyógyszerrel vagy orvostechnikai eszközzel történő kezeléshez fűződő kockázatokat.</P>
               <P>X Gyorsított eljárás.</P>
               <P>Indokolás: Mind a hét részre érvényes körülmény, szükséges a kezelések gyors elérhetővé tétele, így biztosítható egyes hematológiai, primer immunhiányos, valamint a Kawasaki szindrómás betegek széleskörű ellátása a természetben biztosított gyógyszerekkel 2017. november 1-jétől. A hatékonyabb kezelés életeket menthet, és gyorsabb gyógyulásához vezethet. A hivatkozott indikációkban szenvedő betegek gyógyszerhez jutásában az idő kulcsfontosságú, a kezelés késleltetése súlyos vagy maradandó egészségromlást okozhat, illetve a gyógyszeres ellátás hiánya irreverzibilis folyamatokat indíthat el, és a várható élettartamot és emellett.</P>
            </ACCELERATED_PROC>
            <FRAMEWORK>
               <SINGLE_OPERATOR/>
            </FRAMEWORK>
            <CONTRACT_COVERED_GPA/>
            <DATE_RECEIPT_TENDERS>2018-01-22</DATE_RECEIPT_TENDERS>
            <TIME_RECEIPT_TENDERS>10:00</TIME_RECEIPT_TENDERS>
            <DATE_DISPATCH_INVITATIONS>2018-02-22</DATE_DISPATCH_INVITATIONS>
            <LANGUAGES>
               <LANGUAGE VALUE="HU"/>
            </LANGUAGES>
            <DURATION_TENDER_VALID TYPE="MONTH">2</DURATION_TENDER_VALID>
         </PROCEDURE>
         <COMPLEMENTARY_INFO>
            <NO_RECURRENT_PROCUREMENT/>
            <INFO_ADD>
               <P>1. Keretmegállapodás (a továbbiakban KM) megkötésére irányuló, gyorsított, tárgyalásos eljárás: Kbt.85.§(1)c) és a 105.§(1)a) szerint.</P>
               <P>2. Hiánypótlás: Kbt.71.§,Kbt.71.§(5)-(6)szerint. Kieg.tájék: Kbt.56.§, kozbeszerzes@neak.gov.hu címen (legalább fok.biztonságú elektr.aláírással ell.) v.faxon a +36(1)2982463 számon.</P>
               <P>3. A jelentkezésbe (a továbbiakban: ”J”) csatolandó: Kbt.66.§(4), Kbt.68.§(5) szerinti felolvasólap!</P>
               <P>4. Dokumentum benyújtás: Kbt.47.§(2), KR.3.§, 4.§(1),8-16.§ szerint!</P>
               <P>5. A „J”-t Kbt.68.§(2) szerinti 1 eredeti pld.-ban és 2 pld. el. formában is be kell nyújt.</P>
               <P>6. A KR.13.§ alapján foly.-ban lévő változásbejegyzési elj. esetében csatolni kell a cégbír-hoz benyújtott változásbej.-i kérelmet és a cégbír. megküldött igazolását a beérk.-ről.</P>
               <P>7. AK az alkalmassági feltételeket a minősített ajánlattevők jegyzékéhez képest a III.1.3. pontjában szig.hat.meg.</P>
               <P>8. AK a közbesz. dok.teljes terj.-ben elektronikusan, térítésmentesen a honlapján teszi közzé. AK előírja, hogy a részv.jelentkezés hat.lejártáig a közbeszerzési dok.-kat legalább egy részvételre jelentkezőnek v. megnev. alváll.-nak elektr.úton el kell érnie. A hiánytalanul kitöltött reg. adatlapot részvételre jelentkező a közbesz. dok.-ok honlapról tört. letöltését köv. küldje meg AK rész. a kozbeszerzes@neak.gov.hu címre (legalább fok. biztonságú elektronikus aláírással ellátva), vagy faxon a +36 12982463 számra. A Regisztrációs Adatlap (a továbbiakban: RA) megküldése AK részére az ajánlattétel feltétele. AK a RA a kozbeszerzes@neak.gov.hu címre tört. beérk-ről visszaig-t küld a RA-n megjelölt kapcsolattartó részére.</P>
               <P>9. A „J” benyújt.címe: NEAK Közb.Főo., 1139 Budapest, Váci út 73/A., I.em.174.ir. A „J” bontásának ideje, helye 2018.01.22. 10:00 óra, NEAK székhely 246. tárgyaló – jelenlétre jogosultak: Kbt. 68.§(1)-(6) szerint.</P>
               <P>10. A „J” benyújtásának és bontásának helye nem egyezik meg!</P>
               <P>11. Becsült érték: Kbt.19.§(2)-(3) szer.,figy:Kbt.28.§(2). Az egyedüli ért.-i szempont Kbt.76.§(6)a) szerinti legalacsonyabb nettó ár.</P>
               <P>12. Nyertes Ajánlattevő a szerz. telj.-nek teljes időtartama alatt tulajdonosi szerkezetét AK (Vevő) számára megismerhetővé teszi. AK a Kbt. 69. § (11) szerint ellenőriz!</P>
               <P>13. Kbt. 73. § (4)-(5) szerint a szerződés teljesítése során meg kell felelni. Kbt.73.§ (1)e): érvénytelen a „J”, ha nem felel meg a fent előírtaknak!</P>
               <P>14. AK nem írja elő ajánlati biztosíték benyújtását.</P>
               <P>15. AK-t a Kbt. 143.§(2)-(3) szerinti ügyletekről haladéktalanul értesíti.</P>
               <P>16. Felelős akkreditált közbeszerzési szaktanácsadó: Mészáros Róbert (00819.).</P>
               <P>17. Kbt.35.§(8)-(9): AK a szerz. telj. érd.-ben nem teszi lehetővé, nem köv. meg gazdálkodó szerv. létrehozását.</P>
               <P>18. A Kbt.62.§(1-2) kizáró okok igaz. 321/2015.(X.30.)Kr.8.-16.§ szt. AK a Kbt.105§(1)a)pont szt keretmeg.-t kíván kötni, mely terhére közvetlen megrendelés bonyolítható.</P>
               <P>19. AK nem alkalmazza a 75.§(2)e) pontban foglaltakat.</P>
            </INFO_ADD>
            <ADDRESS_REVIEW_BODY>
               <OFFICIALNAME>Közbeszerzési Döntőbizottság</OFFICIALNAME>
               <ADDRESS>Riadó u. 5.</ADDRESS>
               <TOWN>Budapest</TOWN>
               <POSTAL_CODE>1026</POSTAL_CODE>
               <COUNTRY VALUE="HU"/>
               <PHONE>+36 18822594</PHONE>
               <E_MAIL>dontobizottság@kt.hu</E_MAIL>
               <FAX>+36 18822593</FAX>
            </ADDRESS_REVIEW_BODY>
            <REVIEW_PROCEDURE>
               <P>A Kbt 148.§ ban foglaltak szerint.</P>
               <P>Hivatalos név: Közbeszerzési Döntőbizottság.</P>
               <P>Postai cím: Riadó utca 5.</P>
               <P>Város: Budapest.</P>
               <P>Postai irányítószám: 1026.</P>
               <P>Ország: HU.</P>
               <P>Telefon: +36 18828594.</P>
               <P>E-mail: dontobizottsag@kt.hu</P>
               <P>Fax: +36 18828593.</P>
               <P>Internetcím (URL): www.kozbeszerzes.hu.</P>
            </REVIEW_PROCEDURE>
            <ADDRESS_REVIEW_INFO>
               <OFFICIALNAME>Közbeszerzési Döntőbizottság</OFFICIALNAME>
               <ADDRESS>Riadó u. 5.</ADDRESS>
               <TOWN>Budapest</TOWN>
               <POSTAL_CODE>1026</POSTAL_CODE>
               <COUNTRY VALUE="HU"/>
               <PHONE>+36 18828594</PHONE>
               <E_MAIL>dontobizottsag@kt.hu</E_MAIL>
               <FAX>+36 18828593</FAX>
            </ADDRESS_REVIEW_INFO>
            <DATE_DISPATCH_NOTICE>2018-01-05</DATE_DISPATCH_NOTICE>
         </COMPLEMENTARY_INFO>
      </F02_2014>
   </FORM_SECTION>
</TED_EXPORT>
